ngc/Android.py
ngc/Astro.py
ngc/Doc.py
ngc/Lang.py
ngc/Media.py
ngc/UI.py
ngc/Windows.py
ngc/__init__.py
ngc/bin.py
ngc/tst.py
ngc/web.py
ngc-0.21.dist-info/METADATA
ngc-0.21.dist-info/WHEEL
ngc-0.21.dist-info/top_level.txt
ngc-0.21.dist-info/RECORD
