Metadata-Version: 2.1
Name: ngc
Version: 0.21
Summary: Python New General Common Tool
Home-page: https://github.com/ngc5139/pyngc
Author: NGC5139
Author-email: cencrx@outlook.com
Requires-Python: >=3.8
Requires-Dist: requests
